dweb/__init__.py
dweb/_client_manager.py
dweb/aio/__init__.py
dweb/aio/autonomi.py
dweb/autonomi.py
dweb/autonomi.pyi
dweb/errors.py
dweb/network.py
dweb/py.typed
dweb-0.2.1.dist-info/METADATA
dweb-0.2.1.dist-info/WHEEL
dweb-0.2.1.dist-info/RECORD
