Metadata-Version: 2.3
Name: dweb
Version: 0.2.1
Summary: 
License: MIT
Author: Your Name
Author-email: you@example.com
Requires-Python: >=3.11,<4.0
Classifier: License :: OSI Approved :: MIT License
Classifier: Programming Language :: Python :: 3
Classifier: Programming Language :: Python :: 3.11
Classifier: Programming Language :: Python :: 3.12
Classifier: Programming Language :: Python :: 3.13
Requires-Dist: autonomi-client (>=0.5.3,<0.6.0)
